<?xml version="1.0" encoding="ISO-8859-1"?>
<monster name="Arcangel Metal" nameDescription="Arcangel Metal" race="blood" experience="2100000" speed="560">
	<health now="700000" max="700000" />
	<look type="2444" corpse="15224" />
	<targetchange interval="2000" chance="50" />
	<flags>
		<flag summonable="0" />
		<flag attackable="1" />
		<flag hostile="1" />
		<flag illusionable="0" />
		<flag convinceable="0" />
		<flag pushable="1" />
		<flag canpushitems="1" />
		<flag canpushcreatures="1" />
		<flag targetdistance="0" />
		<flag runonhealth="60" />
		<flag isboss="1" />
	</flags>
	<attacks>
		<attack name="melee" interval="2000" min="-23120" max="-31200" poison="360" />
		<attack name="death" interval="3000" chance="23" range="7" radius="7" target="1" min="-22300" max="-43800">
			<attribute key="shootEffect" value="suddendeath" />
			<attribute key="areaEffect" value="mortarea" />
		</attack>
		<attack name="manadrain" interval="3500" chance="20" range="7" radius="6" target="1" min="-32200" max="-23600">
			<attribute key="shootEffect" value="suddendeath" />
			<attribute key="areaEffect" value="bigclouds" />
		</attack>
		<attack name="earth" interval="2000" chance="25" range="7" radius="1" target="1" min="-32200" max="-23800">
			<attribute key="shootEffect" value="poisonarrow" />
			<attribute key="areaEffect" value="greenbubble" />
		</attack>
		<attack name="ice" interval="1200" chance="30" length="8" spread="0" min="-26300" max="-31300">
			<attribute key="areaEffect" value="giantice" />
		</attack>
		<attack name="lifedrain" interval="2000" chance="14" length="8" spread="3" min="-32600" max="-21600">
			<attribute key="areaEffect" value="icetornado" />
		</attack>
	</attacks>
	<defenses armor="40" defense="40">
		<defense name="healing" interval="1000" chance="15" min="10000" max="21000">
			<attribute key="areaEffect" value="blueshimmer" />
		</defense>
	</defenses>
	<elements>
		<element earthPercent="-20" />
		<element energyPercent="-20" />
		<element physicalPercent="-20" />
		<element deathPercent="-20" />
	</elements>
	<immunities>
		<immunity ice="1" />
		<immunity paralyze="1" />
		<immunity drown="1" />
		<immunity fire="1" />
		<immunity invisible="1" />
	</immunities>
	<loot>
		<item name="deepling axe" chance="14285" />
		<item name="depth scutum" chance="100000" />
		<item name="ornate legs" chance="14285" />
	</loot>
</monster>
